operation_log/__init__.py
operation_log/operation_log.py
operation_log-0.2.2.dist-info/LICENSE
operation_log-0.2.2.dist-info/METADATA
operation_log-0.2.2.dist-info/WHEEL
operation_log-0.2.2.dist-info/top_level.txt
operation_log-0.2.2.dist-info/RECORD
