Metadata-Version: 2.1
Name: operation-log
Version: 0.2.2
Summary: A operation log package
Home-page: https://github.com/amuwall/operation_log
Author: amuwall
Author-email: amuwall@outlook.com
Project-URL: Bug Tracker, https://github.com/amuwall/operation_log/issues
Classifier: Programming Language :: Python :: 3
Classifier: License :: OSI Approved :: MIT License
Classifier: Operating System :: OS Independent
Requires-Python: >=3.7
License-File: LICENSE
Requires-Dist: Jinja2
